[
  {
    "filename": "sandboxexample.png",
    "url": "https://res.cloudinary.com/drssjjayn/image/upload/v1757103431/gd8zneen2fq1g2xcbgsl.png",
    "uploaded_at": "2025-09-05T20:17:13.377Z"
  },
  {
    "filename": "productionexample.png",
    "url": "https://res.cloudinary.com/drssjjayn/image/upload/v1757103435/zmiwyqruvgib9q6xljve.png",
    "uploaded_at": "2025-09-05T20:17:15.902Z"
  },
  {
    "filename": "WhatsApp Image 2025-08-25 at 2.22.52 PM.jpeg",
    "url": "https://res.cloudinary.com/drssjjayn/image/upload/v1757103440/qnhyu0roqunqoaxmzz7x.jpg",
    "uploaded_at": "2025-09-05T20:17:21.211Z"
  }
]